nowpayment/__init__.py
nowpayment/decorators.py
nowpayment/models.py
nowpayment/apis/__init__.py
nowpayment/apis/billing.py
nowpayment/apis/currencies.py
nowpayment/apis/payment.py
nowpayment/apis/payout.py
nowpayment-1.6.1.dist-info/METADATA
nowpayment-1.6.1.dist-info/WHEEL
nowpayment-1.6.1.dist-info/top_level.txt
nowpayment-1.6.1.dist-info/RECORD
