Metadata-Version: 2.1
Name: nowpayment
Version: 1.6.1
Summary: A NowPayments.io client for Python
Home-page: https://github.com/its0x4d/nowpayments
Author: Mostafa Mosavi
Author-email: mostafa.uwsgi@gmail.com
License: MIT
Classifier: Programming Language :: Python :: 3
Classifier: License :: OSI Approved :: MIT License
Classifier: Operating System :: OS Independent
Requires-Python: >=3.6
Requires-Dist: requests==2.28.1
